mahesh/__init__.py
mahesh/maheshg.py
mahesh-0.3.0.dist-info/METADATA
mahesh-0.3.0.dist-info/WHEEL
mahesh-0.3.0.dist-info/entry_points.txt
mahesh-0.3.0.dist-info/top_level.txt
mahesh-0.3.0.dist-info/RECORD
